speechless/__init__.py
speechless/__version__.py
speechless/agents/__init__.py
speechless/agents/utils.py
speechless/agents/algorithms/DFS.py
speechless/agents/algorithms/Tree.py
speechless/agents/algorithms/__init__.py
speechless/agents/algorithms/base_env.py
speechless/agents/algorithms/base_search.py
speechless/agents/algorithms/rank_candidate.py
speechless/agents/algorithms/single_chain.py
speechless/agents/functionary/__init__.py
speechless/agents/llms/__init__.py
speechless/agents/llms/base_io.py
speechless/agents/llms/chatgpt_function_model.py
speechless/agents/llms/compression.py
speechless/agents/llms/llama_model.py
speechless/agents/llms/model_adapter.py
speechless/agents/llms/retriever.py
speechless/agents/llms/tool_llama_lora_model.py
speechless/agents/llms/tool_llama_model.py
speechless/agents/llms/utils.py
speechless/agents/llms/vllm_model.py
speechless/agents/octopus/__init__.py
speechless/agents/octopus/octopusv2.py
speechless/agents/openfunctionsv2/__init__.py
speechless/agents/prompts/ReAct_prompts.py
speechless/agents/prompts/Tree_search_prompts.py
speechless/agents/prompts/__init__.py
speechless/agents/prompts/rank_prompts.py
speechless/agents/prompts/tool_conversation.py
speechless/agents/rapidapi/__init__.py
speechless/agents/rapidapi/rapidapi_server.py
speechless/agents/rapidapi/run_rapidapi.py
speechless/agents/rapidapi/toolbench_cache.py
speechless/agents/tooleval/__init__.py
speechless/agents/tooleval/automatic_eval_sample.py
speechless/agents/tooleval/convert_answers.py
speechless/agents/tooleval/convert_to_answer_format.py
speechless/agents/tooleval/eval_and_update_leaderboard.py
speechless/agents/tooleval/eval_pass_rate.py
speechless/agents/tooleval/eval_preference.py
speechless/agents/tooleval/evaluators_comparison.py
speechless/agents/tooleval/utils.py
speechless/agents/tooleval/dataset/__init__.py
speechless/agents/tooleval/evaluation/__init__.py
speechless/agents/tooleval/evaluation/dataclass.py
speechless-0.9.0.dist-info/LICENSE
speechless-0.9.0.dist-info/METADATA
speechless-0.9.0.dist-info/WHEEL
speechless-0.9.0.dist-info/top_level.txt
speechless-0.9.0.dist-info/RECORD
