Metadata-Version: 2.1
Name: speechless
Version: 0.9.0
Summary: LLM based agents with proactive interactions, long-term memory, external tool integration, and local deployment capabilities.
Home-page: https://github.com/uukuguy/speechless
Author: Jiangwen Su
Author-email: uukuguy@gmail.com
License: Apache
Classifier: Intended Audience :: Developers
Classifier: License :: OSI Approved :: Apache Software License
Classifier: Operating System :: OS Independent
Classifier: Programming Language :: Python :: 3
Classifier: Programming Language :: Python :: 3.8
Classifier: Programming Language :: Python :: 3.9
Classifier: Programming Language :: Python :: 3.10
Classifier: Programming Language :: Python :: 3.11
Classifier: Topic :: Scientific/Engineering :: Artificial Intelligence
Requires-Python: >=3.8.0
License-File: LICENSE
Requires-Dist: tqdm >=4.27
Requires-Dist: loguru
Requires-Dist: rich
Requires-Dist: torch >=2.0.1
Requires-Dist: transformers >=4.34.0
Requires-Dist: tokenizers >=0.14.0
Requires-Dist: datasets >=2.14.0
Requires-Dist: flash-attn >=2.3.1
Requires-Dist: bitsandbytes >=0.41.1
Requires-Dist: fastapi
